{
	"name": "ts_tweaks",
	"version": "0.0.41",
	"title": "TS Tweaks",
	"author": "TSomKes",
	"description": "Arbitrary, contentious UI tweaks.  Rearrange crafting item locations to fit my own preferences.",
	"dependencies": [
		"base >= 0.17",
		"? aai-industry >= 0.3.23",
		"? AfraidOfTheDark >= 1.0.23",
		"? Aircraft >= 1.6.11",
		"? angelsaddons-oresilos >= 0.5.1",
		"? angelsaddons-pressuretanks >= 0.4.1",
		"? angelsaddons-warehouses >= 0.4.1",
		"? angelsbioprocessing >= 0.6.2",
		"? angelspetrochem >= 0.8.6",
		"? angelsrefining >= 0.10.14",
		"? angelssmelting >= 0.5.7",
		"? angelssmelting-extended-upgradet >= 0.0.7",
		"? bobassembly >= 0.17.7",
		"? bobelectronics >= 0.17.6",
		"? bobenemies >= 0.17.7",
		"? bobequipment >= 0.17.2",
		"? bobgreenhouse >= 0.17.1",
		"? boblogistics >= 0.17.16",
		"? bobmodules >= 0.17.4",
		"? bobmining >= 0.17.5",
		"? bobores >= 0.17.5",
		"? bobplates >= 0.17.11",
		"? bobpower >= 0.17.10",
		"? bobrevamp >= 0.17.7",
		"? bobsflowcontrol-updated >= 1.0.5",
		"? bobtech >= 0.17.6",
		"? bobvehicleequipment >= 0.17.5",
		"? bobwarfare >= 0.17.11",
		"? CircuitProcessing >= 0.2.1",
		"? color-coding >= 1.17.0",
		"? Energy_Efficient_Beacons >= 0.17.3",
		"? Factorissimo2 >= 2.3.7",
		"? Flow Control >= 3.0.5",
		"? KS_Power >= 0.3.5",
		"? LogisticTrainNetwork >= 1.11.1",
		"? Manganese_Chrome_Sorting >= 0.17.2",
		"? miniloader >= 1.8.3",
		"? Nanobots >= 3.1.0",
		"? Orbital Ion Cannon >= 1.7.2",
		"? Repair_Turret >= 0.2.0",
		"? Rocket-Silo-Construction >= 0.17.13",
		"? ScienceCostTweakerM >= 0.17.10",
		"? SpaceMod >= 0.4.4"
	],
	"factorio_version": "0.17"
}
